hab_gui/__init__.py
hab_gui/cli.py
hab_gui/settings.py
hab_gui/utils.py
hab_gui/version.py
hab_gui/actions/__init__.py
hab_gui/actions/edit_custom_variables_action.py
hab_gui/actions/refresh_action.py
hab_gui/actions/separator_action.py
hab_gui/actions/verbosity_action.py
hab_gui/dialogs/__init__.py
hab_gui/dialogs/error_message_box.py
hab_gui/dialogs/uri_picker_dialog.py
hab_gui/entry_points/base_init.py
hab_gui/entry_points/logging_exception.py
hab_gui/entry_points/message_box.py
hab_gui/resources/README.md
hab_gui/resources/arrow-left-top-bold.svg
hab_gui/resources/content-save.svg
hab_gui/resources/habihat-white.svg
hab_gui/resources/habihat.svg
hab_gui/resources/menu.svg
hab_gui/resources/minus-thick.svg
hab_gui/resources/pencil-box-outline.svg
hab_gui/resources/pin-off-outline.svg
hab_gui/resources/pin-outline.svg
hab_gui/resources/plus-thick.svg
hab_gui/resources/refresh.svg
hab_gui/widgets/__init__.py
hab_gui/widgets/alias_button.py
hab_gui/widgets/alias_button_grid.py
hab_gui/widgets/alias_icon_button.py
hab_gui/widgets/distro_picker.py
hab_gui/widgets/menu_button.py
hab_gui/widgets/name_picker.py
hab_gui/widgets/pinned_uris_button.py
hab_gui/widgets/splash_screen.py
hab_gui/widgets/uri_combobox.py
hab_gui/widgets/uri_line_edit.py
hab_gui/widgets/custom_variable_editor/__init__.py
hab_gui/widgets/custom_variable_editor/custom_variable_editor.py
hab_gui/widgets/custom_variable_editor/file_tree_widget_item.py
hab_gui/widgets/custom_variable_editor/variable_tree_widget_item.py
hab_gui/widgets/custom_variable_editor/ui/custom_variable_editor.ui
hab_gui/widgets/ui/name_picker.ui
hab_gui/windows/__init__.py
hab_gui/windows/alias_launch_window.py
hab_gui-0.26.0.dist-info/licenses/LICENSE
hab_gui-0.26.0.dist-info/METADATA
hab_gui-0.26.0.dist-info/WHEEL
hab_gui-0.26.0.dist-info/entry_points.txt
hab_gui-0.26.0.dist-info/top_level.txt
hab_gui-0.26.0.dist-info/RECORD
