Metadata-Version: 2.4
Name: hab_gui
Version: 0.26.0
Summary: GUI for user interaction to Hab.
Author-email: Blur Studio <opensource@blur.com>
License: LGPL-3.0
Project-URL: Homepage, https://github.com/blurstudio/hab-gui
Project-URL: Source, https://github.com/blurstudio/hab-gui
Project-URL: Tracker, https://github.com/blurstudio/hab-gui/issues
Platform: any
Classifier: Development Status :: 3 - Alpha
Classifier: Environment :: Console
Classifier: Intended Audience :: Developers
Classifier: License :: OSI Approved :: GNU Lesser General Public License v3 (LGPLv3)
Classifier: Operating System :: OS Independent
Classifier: Programming Language :: Python
Classifier: Programming Language :: Python :: 3
Classifier: Programming Language :: Python :: 3 :: Only
Classifier: Programming Language :: Python :: Implementation :: CPython
Classifier: Programming Language :: Python :: Implementation :: PyPy
Requires-Python: >=3.7
License-File: LICENSE
Requires-Dist: click>=7.1.2
Requires-Dist: hab>=0.41.0
Requires-Dist: Pygments
Requires-Dist: Qt.py
Provides-Extra: dev
Requires-Dist: black==22.12.0; extra == "dev"
Requires-Dist: build; extra == "dev"
Requires-Dist: covdefaults; extra == "dev"
Requires-Dist: coverage; extra == "dev"
Requires-Dist: flake8==5.0.4; extra == "dev"
Requires-Dist: flake8-bugbear==22.12.6; extra == "dev"
Requires-Dist: Flake8-pyproject; extra == "dev"
Requires-Dist: isort; extra == "dev"
Requires-Dist: json5; extra == "dev"
Requires-Dist: pep8-naming==0.13.3; extra == "dev"
Requires-Dist: pytest; extra == "dev"
Requires-Dist: tox; extra == "dev"
Requires-Dist: build; extra == "dev"
Provides-Extra: json5
Requires-Dist: pyjson5; extra == "json5"
Dynamic: license-file
